enma/__init__.py
enma/_version.py
enma/application/core/handlers/error.py
enma/application/core/interfaces/downloader_adapter.py
enma/application/core/interfaces/manga_repository.py
enma/application/core/interfaces/saver_adapter.py
enma/application/core/interfaces/use_case.py
enma/application/core/utils/logger.py
enma/application/use_cases/download_chapter.py
enma/application/use_cases/fetch_chapter_by_symbolic_link.py
enma/application/use_cases/get_author_page.py
enma/application/use_cases/get_manga.py
enma/application/use_cases/get_random.py
enma/application/use_cases/paginate.py
enma/application/use_cases/search_manga.py
enma/domain/entities/author_page.py
enma/domain/entities/base.py
enma/domain/entities/manga.py
enma/domain/entities/pagination.py
enma/domain/entities/search_result.py
enma/domain/utils/mime.py
enma/infra/adapters/downloaders/default.py
enma/infra/adapters/downloaders/manganato.py
enma/infra/adapters/repositories/mangadex.py
enma/infra/adapters/repositories/manganato.py
enma/infra/adapters/repositories/nhentai.py
enma/infra/adapters/storage/google_drive.py
enma/infra/adapters/storage/local.py
enma/infra/core/interfaces/lib.py
enma/infra/core/interfaces/mangadex_response.py
enma/infra/core/interfaces/nhentai_response.py
enma/infra/core/utils/cache.py
enma/infra/entrypoints/lib/__init__.py
enma-2.4.4.dist-info/METADATA
enma-2.4.4.dist-info/WHEEL
enma-2.4.4.dist-info/top_level.txt
enma-2.4.4.dist-info/RECORD
