Metadata-Version: 2.1
Name: enma
Version: 2.4.4
Summary: Enma is a Python library designed to fetch manga and doujinshi data from many sources.
Home-page: https://github.com/AlexandreSenpai/Enma
Author: AlexandreSenpai
Author-email: alexandrebsramos@hotmail.com
License: LICENSE
Classifier: Programming Language :: Python :: 3
Classifier: License :: OSI Approved :: MIT License
Classifier: Operating System :: OS Independent
Requires-Python: >=3.9
Requires-Dist: requests==2.32.3
Requires-Dist: beautifulsoup4==4.12.3
Requires-Dist: pydantic==2.8.2
Requires-Dist: expiringdict==1.2.2
Provides-Extra: google-drive
Requires-Dist: google-api-python-client>=2.0.0; extra == "google-drive"
Requires-Dist: google-auth-httplib2>=0.1.0; extra == "google-drive"
Requires-Dist: google-auth-oauthlib>=0.4.0; extra == "google-drive"
